srapy/__init__.py
srapy/_version.py
srapy-0.1.19.data/scripts/get-project-sras.py
srapy-0.1.19.data/scripts/get-run.py
srapy-0.1.19.dist-info/LICENSE
srapy-0.1.19.dist-info/METADATA
srapy-0.1.19.dist-info/WHEEL
srapy-0.1.19.dist-info/top_level.txt
srapy-0.1.19.dist-info/RECORD
