Metadata-Version: 2.1
Name: srapy
Version: 0.1.19
Summary: SRApy: Scripts to download SRA files
Home-page: https://github.com/kdmurray91/srapy
Author: Kevin Murray
Author-email: spam@kdmurray.id.au
License: UNKNOWN
Keywords: bioinformatics,SRA,Next-gen Sequencing
Platform: UNKNOWN
Classifier: Programming Language :: Python
Classifier: Programming Language :: Python :: 2
Classifier: Programming Language :: Python :: 3
Classifier: Development Status :: 3 - Alpha
Classifier: Environment :: Console
Classifier: Intended Audience :: Developers
Classifier: Operating System :: OS Independent
Classifier: Topic :: Software Development :: Libraries :: Python Modules
Classifier: Topic :: Scientific/Engineering :: Bio-Informatics
Classifier: License :: OSI Approved :: GNU General Public License v3 or later (GPLv3+)
Requires-Dist: six (<2.0,>=1.9)
Requires-Dist: biopython (>=1.65)
Requires-Dist: docopt (<0.7,>=0.6)
Requires-Dist: lxml (<4.7,>=3.4)
Requires-Dist: progressbar2 (<2.8,>=2.7)
